pdm_self/__init__.py
pdm_self/cli.py
pdm_self/plugin.py
pdm_self-1.1.0.dist-info/entry_points.txt
pdm_self-1.1.0.dist-info/WHEEL
pdm_self-1.1.0.dist-info/METADATA
pdm_self-1.1.0.dist-info/RECORD
